langchain_zenrows/__init__.py
langchain_zenrows/py.typed
langchain_zenrows/zenrows_universal_scraper.py
langchain_zenrows-0.1.0.dist-info/licenses/LICENSE
langchain_zenrows-0.1.0.dist-info/METADATA
langchain_zenrows-0.1.0.dist-info/WHEEL
langchain_zenrows-0.1.0.dist-info/top_level.txt
langchain_zenrows-0.1.0.dist-info/RECORD
