Metadata-Version: 2.4
Name: langchain-zenrows
Version: 0.1.0
Summary: A LangChain integration tool that provides reliable web scraping capabilities at any scale using ZenRows' Universal Scraper API
Author-email: Yuvraj Chandra <support@zenrows.com>
License: MIT
Project-URL: Homepage, https://github.com/ZenRows-Hub/langchain-zenrows
Project-URL: Repository, https://github.com/ZenRows-Hub/langchain-zenrows
Project-URL: Documentation, https://github.com/ZenRows-Hub/langchain-zenrows
Keywords: langchain,zenrows,web scraping,llm,ai,ml,data extraction
Classifier: Development Status :: 4 - Beta
Classifier: Intended Audience :: Developers
Classifier: Topic :: Software Development :: Libraries :: Python Modules
Classifier: License :: OSI Approved :: MIT License
Classifier: Programming Language :: Python :: 3
Classifier: Programming Language :: Python :: 3.9
Classifier: Programming Language :: Python :: 3.10
Classifier: Programming Language :: Python :: 3.11
Classifier: Programming Language :: Python :: 3.12
Requires-Python: >=3.9
License-File: LICENSE
Requires-Dist: langchain-core>=0.3.0
Requires-Dist: requests>=2.31.0
Requires-Dist: pydantic>=2.0
Provides-Extra: test
Requires-Dist: pytest>=7.0; extra == "test"
Requires-Dist: pytest-mock>=3.10.0; extra == "test"
Requires-Dist: pytest-asyncio>=0.21.0; extra == "test"
Requires-Dist: pytest-cov>=4.0; extra == "test"
Requires-Dist: langchain-tests>=0.3.0; extra == "test"
Provides-Extra: dev
Requires-Dist: ruff>=0.1.5; extra == "dev"
Dynamic: license-file
